odoo/addons/l10n_es_coop/__init__.py
odoo/addons/l10n_es_coop/__manifest__.py
odoo11_l10n_es_coop-0.1.1.dist-info/METADATA
odoo11_l10n_es_coop-0.1.1.dist-info/WHEEL
odoo11_l10n_es_coop-0.1.1.dist-info/top_level.txt
odoo11_l10n_es_coop-0.1.1.dist-info/RECORD
