Metadata-Version: 2.1
Name: odoo11-l10n-es-coop
Version: 0.1.1
Summary: Odoo Spanish Localization for Cooperatives
Home-page: https://gitlab.com/coopdevs/odoo11-l10n-es-coop
Author: Coopdevs,Acysos
License: GPL
Platform: UNKNOWN
